datashaper/__init__.py
datashaper/engine/__init__.py
datashaper/engine/pandas/__init__.py
datashaper/engine/pandas/aggregate_mapping.py
datashaper/engine/pandas/filter_df.py
datashaper/engine/types.py
datashaper/engine/verbs/__init__.py
datashaper/engine/verbs/aggregate.py
datashaper/engine/verbs/bin.py
datashaper/engine/verbs/binarize.py
datashaper/engine/verbs/boolean.py
datashaper/engine/verbs/concat.py
datashaper/engine/verbs/convert.py
datashaper/engine/verbs/copy.py
datashaper/engine/verbs/dedupe.py
datashaper/engine/verbs/derive.py
datashaper/engine/verbs/destructure.py
datashaper/engine/verbs/difference.py
datashaper/engine/verbs/drop.py
datashaper/engine/verbs/erase.py
datashaper/engine/verbs/fill.py
datashaper/engine/verbs/filter.py
datashaper/engine/verbs/fold.py
datashaper/engine/verbs/groupby.py
datashaper/engine/verbs/impute.py
datashaper/engine/verbs/intersect.py
datashaper/engine/verbs/join.py
datashaper/engine/verbs/lookup.py
datashaper/engine/verbs/merge.py
datashaper/engine/verbs/onehot.py
datashaper/engine/verbs/orderby.py
datashaper/engine/verbs/parallel_verb.py
datashaper/engine/verbs/pivot.py
datashaper/engine/verbs/print.py
datashaper/engine/verbs/recode.py
datashaper/engine/verbs/rename.py
datashaper/engine/verbs/rollup.py
datashaper/engine/verbs/sample.py
datashaper/engine/verbs/select.py
datashaper/engine/verbs/spread.py
datashaper/engine/verbs/strings/__init__.py
datashaper/engine/verbs/strings/lower.py
datashaper/engine/verbs/strings/replace.py
datashaper/engine/verbs/strings/upper.py
datashaper/engine/verbs/types.py
datashaper/engine/verbs/unfold.py
datashaper/engine/verbs/ungroup.py
datashaper/engine/verbs/unhot.py
datashaper/engine/verbs/union.py
datashaper/engine/verbs/unorder.py
datashaper/engine/verbs/unroll.py
datashaper/engine/verbs/utils/__init__.py
datashaper/engine/verbs/utils/merge_utils.py
datashaper/engine/verbs/utils/unhot_utils.py
datashaper/engine/verbs/verb_input.py
datashaper/engine/verbs/verbs_mapping.py
datashaper-0.0.48.dist-info/METADATA
datashaper-0.0.48.dist-info/WHEEL
datashaper-0.0.48.dist-info/RECORD
