Metadata-Version: 2.1
Name: datashaper
Version: 0.0.48
Summary: This project provides a collection of utilities for doing lightweight data wrangling.
License: MIT
Author: Nathan Evans
Author-email: naevans@microsoft.com
Requires-Python: >=3.10,<4
Classifier: License :: OSI Approved :: MIT License
Classifier: Programming Language :: Python :: 3
Classifier: Programming Language :: Python :: 3.10
Classifier: Programming Language :: Python :: 3.11
Requires-Dist: diskcache (>=5.6.3,<6.0.0)
Requires-Dist: jsonschema (>=4.21.1,<5.0.0)
Requires-Dist: pandas (>=2.2.0,<3.0.0)
Requires-Dist: pyarrow (>=15.0.0,<16.0.0)
